sms_api/__init__.py
sms_api/altiria_client.py
sms_api/exceptions.py
sms_python_client-1.0.4.dist-info/LICENSE
sms_python_client-1.0.4.dist-info/METADATA
sms_python_client-1.0.4.dist-info/WHEEL
sms_python_client-1.0.4.dist-info/top_level.txt
sms_python_client-1.0.4.dist-info/RECORD
