Metadata-Version: 2.1
Name: sms-python-client
Version: 1.0.4
Summary: Client library to send SMS using Altiria SMS API
Home-page: https://github.com/altiria/sms-python-client
Author: altiria
Author-email: soporte@altiria.com
License: UNKNOWN
Platform: UNKNOWN
Classifier: Development Status :: 5 - Production/Stable
Classifier: License :: OSI Approved :: MIT License
Classifier: Topic :: Software Development :: Libraries :: Python Modules
Classifier: Programming Language :: Python :: 2.7
Classifier: Programming Language :: Python :: 3.4
Classifier: Programming Language :: Python :: 3.5
Classifier: Programming Language :: Python :: 3.6
Classifier: Programming Language :: Python :: 3.7
Requires-Dist: requests
